pymavlink/mavtestgen.py
pymavlink/CSVReader.py
pymavlink/mavwp.py
pymavlink/mavutil.py
pymavlink/mavftpfs.py
pymavlink/quaternion.py
pymavlink/mavftp.py
pymavlink/__init__.py
pymavlink/fgFDM.py
pymavlink/rotmat.py
pymavlink/DFReader.py
pymavlink/mavftp_op.py
pymavlink/mavparm.py
pymavlink/setup.py
pymavlink/mavextra.py
pymavlink/mavexpression.py
pymavlink/message_definitions/v1.0/python_array_test.xml
pymavlink/message_definitions/v1.0/paparazzi.xml
pymavlink/message_definitions/v1.0/AVSSUAS.xml
pymavlink/message_definitions/v1.0/ardupilotmega.xml
pymavlink/message_definitions/v1.0/standard.xml
pymavlink/message_definitions/v1.0/loweheiser.xml
pymavlink/message_definitions/v1.0/all.xml
pymavlink/message_definitions/v1.0/ualberta.xml
pymavlink/message_definitions/v1.0/ASLUAV.xml
pymavlink/message_definitions/v1.0/test.xml
pymavlink/message_definitions/v1.0/cubepilot.xml
pymavlink/message_definitions/v1.0/uAvionix.xml
pymavlink/message_definitions/v1.0/icarous.xml
pymavlink/message_definitions/v1.0/development.xml
pymavlink/message_definitions/v1.0/storm32.xml
pymavlink/message_definitions/v1.0/common.xml
pymavlink/message_definitions/v1.0/matrixpilot.xml
pymavlink/message_definitions/v1.0/minimal.xml
pymavlink/message_definitions/v1.0/csAirLink.xml
pymavlink/generator/mavschema.xsd
pymavlink/generator/mavgen_ada.py
pymavlink/generator/mavgen_lua.py
pymavlink/generator/mavgen_cs.py
pymavlink/generator/mavgen_c.py
pymavlink/generator/mavgen_wlua.py
pymavlink/generator/mavgen_java.py
pymavlink/generator/mavgen_javascript.py
pymavlink/generator/__init__.py
pymavlink/generator/mavparse.py
pymavlink/generator/mavcrc.py
pymavlink/generator/mavgen_typescript.py
pymavlink/generator/mavgen_objc.py
pymavlink/generator/mavgen_spin2.py
pymavlink/generator/mavgen_swift.py
pymavlink/generator/mavgen.py
pymavlink/generator/mavtemplate.py
pymavlink/generator/mavgen_cpp11.py
pymavlink/generator/mavgen_javascript_stable.py
pymavlink-2.4.49.dist-info/RECORD
pymavlink-2.4.49.dist-info/WHEEL
pymavlink-2.4.49.dist-info/top_level.txt
pymavlink-2.4.49.dist-info/METADATA
pymavlink-2.4.49.dist-info/licenses/COPYING
