Metadata-Version: 2.1
Name: pymavlink
Version: 2.4.49
Summary: Python MAVLink code
Home-page: https://github.com/ArduPilot/pymavlink/
License: LGPLv3
Classifier: Development Status :: 5 - Production/Stable
Classifier: Environment :: Console
Classifier: Intended Audience :: Science/Research
Classifier: License :: OSI Approved :: GNU Lesser General Public License v3 (LGPLv3)
Classifier: Operating System :: OS Independent
Classifier: Programming Language :: Python :: 3.6
Classifier: Programming Language :: Python :: 3.7
Classifier: Programming Language :: Python :: 3.8
Classifier: Programming Language :: Python :: 3.9
Classifier: Topic :: Scientific/Engineering
License-File: COPYING
Requires-Dist: lxml
Requires-Dist: fastcrc
